pytest_node_dependency/__init__.py
pytest_node_dependency/plugin.py
pytest_node_dependency-1.4.0.dist-info/LICENSE
pytest_node_dependency-1.4.0.dist-info/METADATA
pytest_node_dependency-1.4.0.dist-info/WHEEL
pytest_node_dependency-1.4.0.dist-info/entry_points.txt
pytest_node_dependency-1.4.0.dist-info/top_level.txt
pytest_node_dependency-1.4.0.dist-info/RECORD
