Metadata-Version: 2.1
Name: pytest-node-dependency
Version: 1.4.0
Summary: pytest plugin for controlling execution flow
Home-page: https://github.com/Formartha/pytest-node-dependency
Author: Mor Dabastany
License: MIT
Keywords: pyest-node-dependency
Classifier: Development Status :: 5 - Production/Stable
Classifier: Framework :: Pytest
Classifier: Intended Audience :: Developers
Classifier: Operating System :: POSIX
Classifier: Operating System :: Microsoft :: Windows
Classifier: Operating System :: MacOS :: MacOS X
Classifier: Topic :: Software Development :: Quality Assurance
Classifier: Topic :: Software Development :: Testing
Classifier: Programming Language :: Python :: 3.11
License-File: LICENSE
Requires-Dist: networkx
